__init__.py
dataset/__init__.py
dataset/dataset.py
dbclass/__init__.py
dbclass/dbclass.py
dbclass/dbclass_utils.py
reports/IMG_001_probability_score.py
reports/IMG_001_probability_score_multifeatures.py
reports/plot_classifier_comparison.py
reports/plot_classifier_comparison_dbclass.py
db_classifier-0.0.4.dist-info/LICENSE
db_classifier-0.0.4.dist-info/METADATA
db_classifier-0.0.4.dist-info/WHEEL
db_classifier-0.0.4.dist-info/top_level.txt
db_classifier-0.0.4.dist-info/RECORD
