Metadata-Version: 2.1
Name: db-classifier
Version: 0.0.4
Summary: A Probabilistic Approach to Multiclass Classification with Unknown Instances
Author-email: Weld Lucas Cunha <cunha.lucas012@gmail.com>
Maintainer-email: Weld Lucas Cunha <cunha.lucas012@gmail.com>
License: MIT License
Project-URL: Homepage, https://github.com/dwelcaslu/DBCLASS
Project-URL: Bug Tracker, https://github.com/dwelcaslu/DBCLASS/issues
Classifier: Programming Language :: Python :: 3
Classifier: License :: OSI Approved :: MIT License
Classifier: Operating System :: OS Independent
Requires-Python: >=3.7
License-File: LICENSE
Requires-Dist: matplotlib (==3.7.1)
Requires-Dist: matplotlib-inline (==0.1.6)
Requires-Dist: numpy (==1.24.2)
Requires-Dist: pandas (==2.0.0)
Requires-Dist: scikit-learn (==1.2.2)
Requires-Dist: scipy (==1.10.1)
Requires-Dist: seaborn (==0.12.2)
